ChangeLog
LICENSE
MANIFEST.in
README.md
README.rst
mdToRst
setup.py
mdToRst.egg-info/PKG-INFO
mdToRst.egg-info/SOURCES.txt
mdToRst.egg-info/dependency_links.txt
mdToRst.egg-info/top_level.txt
md_to_rst/__init__.py