Metadata-Version: 1.1
Name: mdToRst
Version: 1.1.0
Summary: Tool and library to convert markdown to restructed text (md to rst)
Home-page: https://github.com/kata198/mdToRst
Author: Tim Savannah
Author-email: kata198@gmail.com
License: LGPLv3
Keywords: markdown,md,restructed,text,rst,convert,mdToRst,documentation,readme,README.md,README.rst
Platform: UNKNOWN
Classifier: Development Status :: 4 - Beta
Classifier: Programming Language :: Python
Classifier: License :: OSI Approved :: GNU General Public License v3 (GPLv3)
Classifier: Programming Language :: Python :: 2
Classifier: Programming Language :: Python :: 2
Classifier: Programming Language :: Python :: 2.7
Classifier: Programming Language :: Python :: 3
Classifier: Programming Language :: Python :: 3.3
Classifier: Programming Language :: Python :: 3.4
Classifier: Programming Language :: Python :: 3.5
Classifier: Programming Language :: Python :: 3.6
Classifier: Intended Audience :: Developers
Classifier: Topic :: Documentation
Classifier: Topic :: Software Development :: Documentation
Classifier: Topic :: Text Processing
Classifier: Topic :: Text Processing :: Markup
Classifier: Topic :: Utilities
Classifier: Topic :: Software Development :: Libraries :: Python Modules
